{
  "swagger": "2.0",
  "info": {
    "title": "n2x-tenant-api",
    "version": "1.0",
    "contact": {
      "name": "n2x-api",
      "url": "https://github.com/n2x-io/x-api"
    },
    "license": {
      "name": "Apache-2.0 License",
      "url": "https://github.com/n2x-io/x-api/blob/master/LICENSE"
    }
  },
  "tags": [
    {
      "name": "TenantAPI"
    }
  ],
  "schemes": [
    "https"
  ],
  "consumes": [
    "application/json"
  ],
  "produces": [
    "application/json"
  ],
  "paths": {
    "/api/v1/accounts/{accountID}/tenants": {
      "post": {
        "summary": "Lists account tenants.",
        "operationId": "TenantAPI_ListTenants",
        "responses": {
          "200": {
            "description": "A successful response.",
            "schema": {
              "$ref": "#/definitions/tenantTenants"
            }
          },
          "default": {
            "description": "An unexpected error response.",
            "schema": {
              "$ref": "#/definitions/googlerpcStatus"
            }
          }
        },
        "parameters": [
          {
            "name": "accountID",
            "in": "path",
            "required": true,
            "type": "string"
          },
          {
            "name": "body",
            "in": "body",
            "required": true,
            "schema": {
              "$ref": "#/definitions/TenantAPIListTenantsBody"
            }
          }
        ],
        "tags": [
          "TenantAPI"
        ]
      }
    },
    "/api/v1/accounts/{accountID}/tenants/{tenantID}": {
      "get": {
        "summary": "Gets a tenant.",
        "operationId": "TenantAPI_GetTenant",
        "responses": {
          "200": {
            "description": "A successful response.",
            "schema": {
              "$ref": "#/definitions/tenantTenant"
            }
          },
          "default": {
            "description": "An unexpected error response.",
            "schema": {
              "$ref": "#/definitions/googlerpcStatus"
            }
          }
        },
        "parameters": [
          {
            "name": "accountID",
            "in": "path",
            "required": true,
            "type": "string"
          },
          {
            "name": "tenantID",
            "in": "path",
            "required": true,
            "type": "string"
          }
        ],
        "tags": [
          "TenantAPI"
        ]
      },
      "delete": {
        "summary": "Deletes a tenant.",
        "operationId": "TenantAPI_DeleteTenant",
        "responses": {
          "200": {
            "description": "A successful response.",
            "schema": {
              "$ref": "#/definitions/emptyResponse"
            }
          },
          "default": {
            "description": "An unexpected error response.",
            "schema": {
              "$ref": "#/definitions/googlerpcStatus"
            }
          }
        },
        "parameters": [
          {
            "name": "accountID",
            "in": "path",
            "required": true,
            "type": "string"
          },
          {
            "name": "tenantID",
            "in": "path",
            "required": true,
            "type": "string"
          }
        ],
        "tags": [
          "TenantAPI"
        ]
      },
      "patch": {
        "summary": "Updates a tenant.",
        "operationId": "TenantAPI_UpdateTenant",
        "responses": {
          "200": {
            "description": "A successful response.",
            "schema": {
              "$ref": "#/definitions/tenantTenant"
            }
          },
          "default": {
            "description": "An unexpected error response.",
            "schema": {
              "$ref": "#/definitions/googlerpcStatus"
            }
          }
        },
        "parameters": [
          {
            "name": "accountID",
            "in": "path",
            "required": true,
            "type": "string"
          },
          {
            "name": "tenantID",
            "in": "path",
            "required": true,
            "type": "string"
          },
          {
            "name": "body",
            "in": "body",
            "required": true,
            "schema": {
              "$ref": "#/definitions/TenantAPIUpdateTenantBody"
            }
          }
        ],
        "tags": [
          "TenantAPI"
        ]
      }
    },
    "/api/v1/accounts/{accountID}/tenants:new": {
      "post": {
        "summary": "Creates a tenant.",
        "operationId": "TenantAPI_CreateTenant",
        "responses": {
          "200": {
            "description": "A successful response.",
            "schema": {
              "$ref": "#/definitions/tenantTenant"
            }
          },
          "default": {
            "description": "An unexpected error response.",
            "schema": {
              "$ref": "#/definitions/googlerpcStatus"
            }
          }
        },
        "parameters": [
          {
            "name": "accountID",
            "in": "path",
            "required": true,
            "type": "string"
          },
          {
            "name": "body",
            "in": "body",
            "required": true,
            "schema": {
              "$ref": "#/definitions/TenantAPICreateTenantBody"
            }
          }
        ],
        "tags": [
          "TenantAPI"
        ]
      }
    },
    "/api/v1/accounts/{accountID}/tenants:topology": {
      "get": {
        "summary": "Gets topology tenant list.",
        "operationId": "TenantAPI_GetTopologyTenantList",
        "responses": {
          "200": {
            "description": "A successful response.",
            "schema": {
              "$ref": "#/definitions/tenantTopologyTenantList"
            }
          },
          "default": {
            "description": "An unexpected error response.",
            "schema": {
              "$ref": "#/definitions/googlerpcStatus"
            }
          }
        },
        "parameters": [
          {
            "name": "accountID",
            "in": "path",
            "required": true,
            "type": "string"
          }
        ],
        "tags": [
          "TenantAPI"
        ]
      }
    }
  },
  "definitions": {
    "TenantAPICreateTenantBody": {
      "type": "object",
      "properties": {
        "name": {
          "type": "string"
        },
        "description": {
          "type": "string"
        }
      }
    },
    "TenantAPIListTenantsBody": {
      "type": "object",
      "properties": {
        "meta": {
          "$ref": "#/definitions/resourceListRequest"
        }
      }
    },
    "TenantAPIUpdateTenantBody": {
      "type": "object",
      "properties": {
        "name": {
          "type": "string"
        },
        "description": {
          "type": "string"
        }
      }
    },
    "emptyResponse": {
      "type": "object"
    },
    "googlerpcStatus": {
      "type": "object",
      "properties": {
        "code": {
          "type": "integer",
          "format": "int32"
        },
        "message": {
          "type": "string"
        },
        "details": {
          "type": "array",
          "items": {
            "type": "object",
            "$ref": "#/definitions/protobufAny"
          }
        }
      }
    },
    "protobufAny": {
      "type": "object",
      "properties": {
        "@type": {
          "type": "string"
        }
      },
      "additionalProperties": {}
    },
    "resourceListRequest": {
      "type": "object",
      "properties": {
        "pageToken": {
          "type": "string"
        },
        "pageSize": {
          "type": "integer",
          "format": "int32"
        }
      }
    },
    "resourceListResponse": {
      "type": "object",
      "properties": {
        "nextPageToken": {
          "type": "string"
        }
      }
    },
    "tenantTenant": {
      "type": "object",
      "properties": {
        "accountID": {
          "type": "string"
        },
        "tenantID": {
          "type": "string"
        },
        "name": {
          "type": "string"
        },
        "description": {
          "type": "string"
        }
      }
    },
    "tenantTenants": {
      "type": "object",
      "properties": {
        "meta": {
          "$ref": "#/definitions/resourceListResponse"
        },
        "tenants": {
          "type": "array",
          "items": {
            "type": "object",
            "$ref": "#/definitions/tenantTenant"
          }
        }
      }
    },
    "tenantTopologyTenantList": {
      "type": "object",
      "properties": {
        "tenants": {
          "type": "array",
          "items": {
            "type": "object",
            "$ref": "#/definitions/tenantTenant"
          }
        }
      }
    }
  }
}
